{
  "collapse-filter": true,
  "search": "",
  "showTags": false,
  "showAttachments": false,
  "hideUnresolved": false,
  "showOrphans": true,
  "collapse-color-groups": false,
  "colorGroups": [
    {
      "query": "tag:#Red",
      "color": {
        "a": 1,
        "rgb": 14048348
      }
    },
    {
      "query": "tag:#Blue",
      "color": {
        "a": 1,
        "rgb": 6058198
      }
    },
    {
      "query": "tag:#Windows  ",
      "color": {
        "a": 1,
        "rgb": 11392604
      }
    },
    {
      "query": "tag:#Linux",
      "color": {
        "a": 1,
        "rgb": 6084188
      }
    }
  ],
  "collapse-display": false,
  "showArrow": true,
  "textFadeMultiplier": -0.6,
  "nodeSizeMultiplier": 1.19679768880208,
  "lineSizeMultiplier": 1.63523763020833,
  "collapse-forces": false,
  "centerStrength": 0.475179036458333,
  "repelStrength": 11.00341796875,
  "linkStrength": 1,
  "linkDistance": 252,
  "scale": 0.013251262680297646,
  "close": true
}